govern/__init__.py
govern/core/__init__.py
govern/stubs/__init__.py
govern-0.0.1.dist-info/LICENSE
govern-0.0.1.dist-info/METADATA
govern-0.0.1.dist-info/WHEEL
govern-0.0.1.dist-info/top_level.txt
govern-0.0.1.dist-info/RECORD
