Metadata-Version: 2.1
Name: govern
Version: 0.0.1
Summary: Model governance AI for quant finance
Home-page: https://github.com/compatibl/govern
Author: The Project Contributors
License: Apache Software License
Project-URL: Source Code, https://github.com/compatibl/govern
Classifier: Development Status :: 3 - Alpha
Classifier: Intended Audience :: Developers
Classifier: Intended Audience :: Science/Research
Classifier: Intended Audience :: Financial and Insurance Industry
Classifier: Topic :: Software Development
Classifier: Topic :: Scientific/Engineering
Classifier: License :: OSI Approved :: Apache Software License
Classifier: Programming Language :: Python :: 3.10
Classifier: Programming Language :: Python :: 3.11
Classifier: Operating System :: OS Independent
License-File: LICENSE
Requires-Dist: langchain >=0.0.285
Requires-Dist: convince >=0.0.1
